matplotlib_tuda/__init__.py
matplotlib_tuda/main.py
matplotlib_tuda-0.0.1.dist-info/LICENSE
matplotlib_tuda-0.0.1.dist-info/METADATA
matplotlib_tuda-0.0.1.dist-info/WHEEL
matplotlib_tuda-0.0.1.dist-info/top_level.txt
matplotlib_tuda-0.0.1.dist-info/RECORD
