Metadata-Version: 2.1
Name: matplotlib-tuda
Version: 0.0.1
Summary: Small package to add the corporate colors of the TU Darmstadt to Matplotlib.
Home-page: https://github.com/fdamken/matplotlib-tuda
Author: Fabian Damken
Author-email: fabian.damken@frisp.org
License: UNKNOWN
Platform: UNKNOWN
Classifier: Programming Language :: Python :: 3
Classifier: License :: OSI Approved :: MIT License
Classifier: Operating System :: OS Independent
Requires-Python: >=3.8
